kunlun/__init__.py
kunlun/__main__.py
kunlun/lib.py
kunlun/main.py
kunlun/version.py
kunlun/assets/nginx.conf
kunlun/httpd/__init__.py
kunlun/httpd/api.cpython-310-x86_64-linux-gnu.so
kunlun/httpd/server.cpython-310-x86_64-linux-gnu.so
kunlun/httpd/ws.cpython-310-x86_64-linux-gnu.so
kunlun/job/__init__.py
kunlun/job/job.cpython-310-x86_64-linux-gnu.so
kunlun/job/task.cpython-310-x86_64-linux-gnu.so
kunlun/job/util.cpython-310-x86_64-linux-gnu.so
kunlun/job/vars.cpython-310-x86_64-linux-gnu.so
kunlun/service/__init__.py
kunlun/service/cli.cpython-310-x86_64-linux-gnu.so
kunlun/service/connection.cpython-310-x86_64-linux-gnu.so
kunlun/service/container.cpython-310-x86_64-linux-gnu.so
kunlun/service/database.cpython-310-x86_64-linux-gnu.so
kunlun/service/gui.cpython-310-x86_64-linux-gnu.so
kunlun/service/locking.cpython-310-x86_64-linux-gnu.so
kunlun/service/logger.cpython-310-x86_64-linux-gnu.so
kunlun/service/message.cpython-310-x86_64-linux-gnu.so
kunlun/service/pyplugin.cpython-310-x86_64-linux-gnu.so
kunlun/service/scheduler.cpython-310-x86_64-linux-gnu.so
kunlun/service/sequence.cpython-310-x86_64-linux-gnu.so
kunlun/service/station.cpython-310-x86_64-linux-gnu.so
kunlun/service/sync.cpython-310-x86_64-linux-gnu.so
kunlun/service/plus/__init__.py
kunlun/service/plus/secure.cpython-310-x86_64-linux-gnu.so
kunlun/session/__init__.py
kunlun/session/bash.cpython-310-x86_64-linux-gnu.so
kunlun/web/favicon.ico
kunlun/web/index.html
kunlun/web/assets/AskQuestion-CjA_xxF0.js
kunlun/web/assets/Connection-BXLToq8Z.js
kunlun/web/assets/Connection-fdtnKind.css
kunlun/web/assets/Container-DEfVi5ss.js
kunlun/web/assets/Container-DxN3YRf-.css
kunlun/web/assets/ErrorNotFound-BuO6rsSv.js
kunlun/web/assets/IndexPage-B_8fMxkJ.js
kunlun/web/assets/KFOMCnqEu92Fr1ME7kSn66aGLdTylUAMQXC89YmC2DPNWuYjalmUiAw-BepdiOnY.woff
kunlun/web/assets/KFOMCnqEu92Fr1ME7kSn66aGLdTylUAMQXC89YmC2DPNWuZtalmUiAw-4ZhHFPot.woff
kunlun-26.1.0.dist-info/METADATA
kunlun-26.1.0.dist-info/WHEEL
kunlun-26.1.0.dist-info/entry_points.txt
kunlun-26.1.0.dist-info/RECORD
