Metadata-Version: 2.4
Name: kunlun
Version: 26.1.0
Summary: KunLun AutoTest
Author-email: robinwu <164391159@163.com>
License-Expression: MIT
Requires-Python: >=3.10
Requires-Dist: addict>=2.4.0
Requires-Dist: aioredis>=2.0.1
Requires-Dist: allure-pytest>=2.15.2
Requires-Dist: apscheduler>=3.11.0
Requires-Dist: cython>=3.1.2
Requires-Dist: flask-cors>=6.0.1
Requires-Dist: flask>=3.1.1
Requires-Dist: gevent>=25.5.1
Requires-Dist: openpyxl>=3.1.5
Requires-Dist: paramiko>=3.5.1
Requires-Dist: psutil>=7.0.0
Requires-Dist: ptyprocess>=0.7.0
Requires-Dist: pytest-order>=1.3.0
Requires-Dist: pytest>=9.0.1
Requires-Dist: redis>=6.2.0
Requires-Dist: requests>=2.32.4
Requires-Dist: serial>=0.0.97
Requires-Dist: websockets>=15.0.1
Requires-Dist: wget>=3.2
Requires-Dist: xmltodict>=1.0.2
